src/__init__.py
src/server.py
amsl_schemas_mcp-0.1.0.dist-info/LICENSE
amsl_schemas_mcp-0.1.0.dist-info/METADATA
amsl_schemas_mcp-0.1.0.dist-info/WHEEL
amsl_schemas_mcp-0.1.0.dist-info/entry_points.txt
amsl_schemas_mcp-0.1.0.dist-info/RECORD
