Metadata-Version: 2.3
Name: amsl-schemas-mcp
Version: 0.1.0
Summary: MCP server for AMSL schema resources and validation
License: MIT
Author: Linus Bierhoff
Author-email: accounts@linusbierhoff.com
Requires-Python: >=3.13
Classifier: License :: OSI Approved :: MIT License
Classifier: Programming Language :: Python :: 3
Classifier: Programming Language :: Python :: 3.13
Requires-Dist: httpx (>=0.24.0)
Requires-Dist: jsonschema (>=4.0)
Requires-Dist: mcp (>=0.1.0)
Requires-Dist: pyyaml (>=6.0)
